bantam/__init__.py
bantam/__main__.py
bantam/bantam_chat.py
bantam/configuration_bantam.py
bantam/export_onnx.py
bantam/modeling_bantam.py
bantam/optimizer.py
bantam/tokenization_bantam.py
bantam/trainer.py
bantam/config_templates/__init__.py
bantam/config_templates/model.yaml
bantam/config_templates/pretrain.yaml
bantam/config_templates/sft.yaml
bantam_cli-0.1.2.dist-info/METADATA
bantam_cli-0.1.2.dist-info/WHEEL
bantam_cli-0.1.2.dist-info/entry_points.txt
bantam_cli-0.1.2.dist-info/top_level.txt
bantam_cli-0.1.2.dist-info/RECORD
