Metadata-Version: 2.4
Name: bantam-cli
Version: 0.1.2
Summary: Bantam language model core
Author-email: Theoistic <theo@theoistic.com>
Requires-Python: >=3.8
Requires-Dist: torch>=2.1.0
Requires-Dist: transformers>=4.40.0
Requires-Dist: datasets>=2.16.0
Requires-Dist: peft>=0.11.0
Requires-Dist: numpy>=1.24.0
Requires-Dist: matplotlib>=3.8.0
Requires-Dist: tqdm>=4.65.0
Requires-Dist: PyYAML>=6.0
Requires-Dist: typer>=0.9.0
